setup.py
tiny_xslt/__init__.py
tiny_xslt.egg-info/PKG-INFO
tiny_xslt.egg-info/SOURCES.txt
tiny_xslt.egg-info/dependency_links.txt
tiny_xslt.egg-info/top_level.txt