Metadata-Version: 1.0
Name: tiny-xslt
Version: 2.0.1
Summary: Easy XSL transformations.
Home-page: https://bitbucket.org/jodier/tiny_xslt
Author: Jerome Odier
Author-email: jerome.odier@cern.ch
License: CeCILL-C
Download-URL: https://pypi.python.org/packages/source/t/tiny_xslt/tiny_xslt-2.0.1.tar.gz
Platform: UNKNOWN
